cloudbridge/__init__.py
cloudbridge/factory.py
cloudbridge/base/__init__.py
cloudbridge/base/helpers.py
cloudbridge/base/middleware.py
cloudbridge/base/provider.py
cloudbridge/base/resources.py
cloudbridge/base/services.py
cloudbridge/base/subservices.py
cloudbridge/interfaces/__init__.py
cloudbridge/interfaces/exceptions.py
cloudbridge/interfaces/provider.py
cloudbridge/interfaces/resources.py
cloudbridge/interfaces/services.py
cloudbridge/interfaces/subservices.py
cloudbridge/providers/__init__.py
cloudbridge/providers/aws/__init__.py
cloudbridge/providers/aws/helpers.py
cloudbridge/providers/aws/provider.py
cloudbridge/providers/aws/resources.py
cloudbridge/providers/aws/services.py
cloudbridge/providers/aws/subservices.py
cloudbridge/providers/azure/__init__.py
cloudbridge/providers/azure/azure_client.py
cloudbridge/providers/azure/helpers.py
cloudbridge/providers/azure/provider.py
cloudbridge/providers/azure/resources.py
cloudbridge/providers/azure/services.py
cloudbridge/providers/azure/subservices.py
cloudbridge/providers/gcp/__init__.py
cloudbridge/providers/gcp/helpers.py
cloudbridge/providers/gcp/provider.py
cloudbridge/providers/gcp/resources.py
cloudbridge/providers/gcp/services.py
cloudbridge/providers/gcp/subservices.py
cloudbridge/providers/mock/__init__.py
cloudbridge/providers/mock/provider.py
cloudbridge/providers/openstack/__init__.py
cloudbridge/providers/openstack/helpers.py
cloudbridge/providers/openstack/provider.py
cloudbridge/providers/openstack/resources.py
cloudbridge/providers/openstack/services.py
cloudbridge/providers/openstack/subservices.py
tests/__init__.py
tests/test_base_helpers.py
tests/test_block_store_service.py
tests/test_cloud_factory.py
tests/test_cloud_helpers.py
tests/test_compute_service.py
tests/test_dns_service.py
tests/test_image_service.py
tests/test_interface.py
tests/test_middleware_system.py
tests/test_network_service.py
tests/test_object_life_cycle.py
tests/test_object_store_service.py
tests/test_region_service.py
cloudbridge-3.2.0.dist-info/LICENSE
cloudbridge-3.2.0.dist-info/METADATA
cloudbridge-3.2.0.dist-info/WHEEL
cloudbridge-3.2.0.dist-info/top_level.txt
cloudbridge-3.2.0.dist-info/RECORD
