Metadata-Version: 2.1
Name: cloudbridge
Version: 3.2.0
Summary: A simple layer of abstraction over multiple cloud providers.
Home-page: http://cloudbridge.cloudve.org/
Author: Galaxy and GVL Projects
Author-email: help@genome.edu.au
License: MIT
Classifier: Development Status :: 5 - Production/Stable
Classifier: Environment :: Console
Classifier: Intended Audience :: Developers
Classifier: Intended Audience :: System Administrators
Classifier: License :: OSI Approved :: MIT License
Classifier: Operating System :: OS Independent
Classifier: Programming Language :: Python
Classifier: Topic :: Software Development :: Libraries :: Python Modules
Classifier: Programming Language :: Python :: 2.7
Classifier: Programming Language :: Python :: 3
Classifier: Programming Language :: Python :: 3.4
Classifier: Programming Language :: Python :: 3.5
Classifier: Programming Language :: Python :: 3.6
Classifier: Programming Language :: Python :: Implementation :: CPython
License-File: LICENSE
Requires-Dist: six >=1.11
Requires-Dist: tenacity >=6.0
Requires-Dist: deprecation >=2.0.7
Requires-Dist: pyeventsystem <2
Requires-Dist: ipaddress ; python_version<"3.3"
Provides-Extra: aws
Requires-Dist: boto3 <2.0.0,>=1.9.86 ; extra == 'aws'
Provides-Extra: azure
Requires-Dist: msrestazure <1.0.0 ; extra == 'azure'
Requires-Dist: azure-identity <2.0.0 ; extra == 'azure'
Requires-Dist: azure-common <2.0.0 ; extra == 'azure'
Requires-Dist: azure-mgmt-devtestlabs <10.0.0 ; extra == 'azure'
Requires-Dist: azure-mgmt-resource <22.0.0 ; extra == 'azure'
Requires-Dist: azure-mgmt-compute <28.0.0,>=27.2.0 ; extra == 'azure'
Requires-Dist: azure-mgmt-network <22.0.0 ; extra == 'azure'
Requires-Dist: azure-mgmt-storage <21.0.0 ; extra == 'azure'
Requires-Dist: azure-storage-blob <13.0.0 ; extra == 'azure'
Requires-Dist: azure-cosmosdb-table <2.0.0 ; extra == 'azure'
Requires-Dist: pysftp <1.0.0 ; extra == 'azure'
Provides-Extra: dev
Requires-Dist: tox >=4.0.0 ; extra == 'dev'
Requires-Dist: pytest ; extra == 'dev'
Requires-Dist: moto >=3.1.18 ; extra == 'dev'
Requires-Dist: sphinx >=1.3.1 ; extra == 'dev'
Requires-Dist: pydevd ; extra == 'dev'
Requires-Dist: flake8 >=3.3.0 ; extra == 'dev'
Requires-Dist: flake8-import-order >=0.12 ; extra == 'dev'
Requires-Dist: boto3 <2.0.0,>=1.9.86 ; extra == 'dev'
Requires-Dist: google-api-python-client <3.0.0,>=2.0 ; extra == 'dev'
Requires-Dist: openstacksdk <1.0.0,>=0.12.0 ; extra == 'dev'
Requires-Dist: python-novaclient <19.0,>=7.0.0 ; extra == 'dev'
Requires-Dist: python-swiftclient <5.0,>=3.2.0 ; extra == 'dev'
Requires-Dist: python-neutronclient <9.0,>=6.0.0 ; extra == 'dev'
Requires-Dist: python-keystoneclient <6.0,>=3.13.0 ; extra == 'dev'
Requires-Dist: msrestazure <1.0.0 ; extra == 'dev'
Requires-Dist: azure-identity <2.0.0 ; extra == 'dev'
Requires-Dist: azure-common <2.0.0 ; extra == 'dev'
Requires-Dist: azure-mgmt-devtestlabs <10.0.0 ; extra == 'dev'
Requires-Dist: azure-mgmt-resource <22.0.0 ; extra == 'dev'
Requires-Dist: azure-mgmt-compute <28.0.0,>=27.2.0 ; extra == 'dev'
Requires-Dist: azure-mgmt-network <22.0.0 ; extra == 'dev'
Requires-Dist: azure-mgmt-storage <21.0.0 ; extra == 'dev'
Requires-Dist: azure-storage-blob <13.0.0 ; extra == 'dev'
Requires-Dist: azure-cosmosdb-table <2.0.0 ; extra == 'dev'
Requires-Dist: pysftp <1.0.0 ; extra == 'dev'
Provides-Extra: full
Requires-Dist: boto3 <2.0.0,>=1.9.86 ; extra == 'full'
Requires-Dist: google-api-python-client <3.0.0,>=2.0 ; extra == 'full'
Requires-Dist: openstacksdk <1.0.0,>=0.12.0 ; extra == 'full'
Requires-Dist: python-novaclient <19.0,>=7.0.0 ; extra == 'full'
Requires-Dist: python-swiftclient <5.0,>=3.2.0 ; extra == 'full'
Requires-Dist: python-neutronclient <9.0,>=6.0.0 ; extra == 'full'
Requires-Dist: python-keystoneclient <6.0,>=3.13.0 ; extra == 'full'
Requires-Dist: msrestazure <1.0.0 ; extra == 'full'
Requires-Dist: azure-identity <2.0.0 ; extra == 'full'
Requires-Dist: azure-common <2.0.0 ; extra == 'full'
Requires-Dist: azure-mgmt-devtestlabs <10.0.0 ; extra == 'full'
Requires-Dist: azure-mgmt-resource <22.0.0 ; extra == 'full'
Requires-Dist: azure-mgmt-compute <28.0.0,>=27.2.0 ; extra == 'full'
Requires-Dist: azure-mgmt-network <22.0.0 ; extra == 'full'
Requires-Dist: azure-mgmt-storage <21.0.0 ; extra == 'full'
Requires-Dist: azure-storage-blob <13.0.0 ; extra == 'full'
Requires-Dist: azure-cosmosdb-table <2.0.0 ; extra == 'full'
Requires-Dist: pysftp <1.0.0 ; extra == 'full'
Provides-Extra: gcp
Requires-Dist: google-api-python-client <3.0.0,>=2.0 ; extra == 'gcp'
Provides-Extra: openstack
Requires-Dist: openstacksdk <1.0.0,>=0.12.0 ; extra == 'openstack'
Requires-Dist: python-novaclient <19.0,>=7.0.0 ; extra == 'openstack'
Requires-Dist: python-swiftclient <5.0,>=3.2.0 ; extra == 'openstack'
Requires-Dist: python-neutronclient <9.0,>=6.0.0 ; extra == 'openstack'
Requires-Dist: python-keystoneclient <6.0,>=3.13.0 ; extra == 'openstack'
